nemli-0.1.0.dist-info/METADATA
nemli-0.1.0.dist-info/WHEEL
nemli-0.1.0.dist-info/entry_points.txt
nemli/__init__.py
nemli/commands/utility/__init__.py
nemli/commands/utility/help.py
nemli/commands/utility/ping.py
nemli/commands/utility/summarize.py
nemli/config.py
nemli/main.py
nemli/nlp/messages.py
nemli/schemas/messages.py
nemli/services/messages.py
nemli-0.1.0.dist-info/RECORD
