Metadata-Version: 2.1
Name: nemli
Version: 0.1.0
Summary: Um bot de discord para criar resumos baseado nas últimas mensagens de um canal
Author-Email: Manoel Vilela <manoel_vilela@engineer.com>, Mateus Reis <mateuspsvreis@gmail.com>
License: MIT
Requires-Python: >=3.10
Requires-Dist: pydantic-settings>=2.3.4
Requires-Dist: openai>=1.37.0
Requires-Dist: nextcord>=2.6.0
Requires-Dist: setuptools>=71.1.0
Requires-Dist: nltk>=3.8.1
